LICENSE
MANIFEST.in
README.md
requirements.txt
setup.cfg
setup.py
amqp_client_cli/__init__.py
amqp_client_cli/main.py
amqp_client_cli.egg-info/PKG-INFO
amqp_client_cli.egg-info/SOURCES.txt
amqp_client_cli.egg-info/dependency_links.txt
amqp_client_cli.egg-info/entry_points.txt
amqp_client_cli.egg-info/requires.txt
amqp_client_cli.egg-info/top_level.txt