Metadata-Version: 1.1
Name: amqp-client-cli
Version: 0.3
Summary: A command line interface for interacting with amqp exchanges
Home-page: https://github.com/ownaginatious/amqp-client-cli
Author: Dillon Dixon
Author-email: dillondixon@gmail.com
License: MIT
Keywords: amqp,cli,client,rabbitmq,amq
Platform: UNKNOWN
Classifier: Environment :: Console
